paylink/__init__.py
paylink/client.py
paylink/config.py
paylink/mcp_monitization/__init__.py
paylink/mcp_monitization/adapter.py
paylink/mcp_monitization/payments.py
paylink/mpesa_tools/__init__.py
paylink/mpesa_tools/client.py
paylink-0.2.2.dist-info/METADATA
paylink-0.2.2.dist-info/WHEEL
paylink-0.2.2.dist-info/licenses/LICENSE
paylink-0.2.2.dist-info/RECORD
