Metadata-Version: 2.4
Name: paylink
Version: 0.2.2
Summary: Python SDK for interacting with PayLink MCP servers
Project-URL: Homepage, https://github.com/yourusername/paylink
Project-URL: Repository, https://github.com/yourusername/paylink
Project-URL: Documentation, https://github.com/yourusername/paylink#readme
Project-URL: Bug Tracker, https://github.com/yourusername/paylink/issues
Author-email: PayLink <paylinkmcp@gmail.com>
Maintainer-email: PayLink <paylinkmcp@gmail.com>
License: MIT License
License-File: LICENSE
Keywords: kenya,mcp,mpesa,paylink,payment,sdk
Classifier: Development Status :: 3 - Alpha
Classifier: Intended Audience :: Developers
Classifier: License :: OSI Approved :: MIT License
Classifier: Operating System :: OS Independent
Classifier: Programming Language :: Python :: 3
Classifier: Programming Language :: Python :: 3.10
Classifier: Programming Language :: Python :: 3.11
Classifier: Programming Language :: Python :: 3.12
Classifier: Topic :: Office/Business :: Financial
Classifier: Topic :: Software Development :: Libraries :: Python Modules
Requires-Python: >=3.10
Requires-Dist: hatch>=1.14.1
Requires-Dist: mcp[cli]>=1.13.1
Requires-Dist: python-dotenv>=1.0.1
Requires-Dist: twine>=6.2.0
